MANIFEST.in
README.md
setup.cfg
setup.py
wafflehaus/__init__.py
wafflehaus.neutron.egg-info/PKG-INFO
wafflehaus.neutron.egg-info/SOURCES.txt
wafflehaus.neutron.egg-info/dependency_links.txt
wafflehaus.neutron.egg-info/namespace_packages.txt
wafflehaus.neutron.egg-info/not-zip-safe
wafflehaus.neutron.egg-info/pbr.json
wafflehaus.neutron.egg-info/requires.txt
wafflehaus.neutron.egg-info/top_level.txt
wafflehaus/neutron/__init__.py
wafflehaus/neutron/context/__init__.py
wafflehaus/neutron/context/neutron_context.py
wafflehaus/neutron/ip_policy/__init__.py
wafflehaus/neutron/ip_policy/create_default.py
wafflehaus/neutron/last_ip_check/__init__.py
wafflehaus/neutron/last_ip_check/last_ip_check.py
wafflehaus/neutron/nova_interaction/__init__.py
wafflehaus/neutron/nova_interaction/common.py
wafflehaus/neutron/pagination/__init__.py
wafflehaus/neutron/pagination/pagination.py
wafflehaus/neutron/shared_network/__init__.py
wafflehaus/neutron/shared_network/trusted.py