Metadata-Version: 1.1
Name: wafflehaus.neutron
Version: 0.1.4
Summary: A collection of middleware for openstack neutron
Home-page: https://github.com/roaet/wafflehaus.neutron
Author: Justin Hammond
Author-email: justin.hammond@rackspace.com
License: Apache Software License
Keywords: openstack
Platform: UNKNOWN
Classifier: Development Status :: 5 - Production/Stable
Classifier: Environment :: Web Environment
Classifier: Framework :: Paste
Classifier: Intended Audience :: Developers
Classifier: Intended Audience :: System Administrators
Classifier: License :: OSI Approved :: Apache Software License
Classifier: Operating System :: OS Independent
Classifier: Programming Language :: Python :: 2.7
Classifier: Programming Language :: Python :: 2.6
Classifier: Topic :: Internet :: WWW/HTTP :: WSGI :: Middleware
